pygrates/__init__.py
pygrates/abc.py
pygrates/collections.py
pygrates/graphs.py
pygrates/itertools.py
pygrates/moves.py
pygrates/py.typed
pygrates-0.2.1.dist-info/LICENSE
pygrates-0.2.1.dist-info/METADATA
pygrates-0.2.1.dist-info/WHEEL
pygrates-0.2.1.dist-info/top_level.txt
pygrates-0.2.1.dist-info/RECORD
