Metadata-Version: 2.1
Name: pygrates
Version: 0.2.1
Summary: Functional and lazy mini-framework for local search on combinatorial problems
Author-email: Koen van Walstijn <kbvw@pm.me>
Project-URL: Source, https://codeberg.org/kbvw/pygrates
Classifier: Programming Language :: Python :: 3
Classifier: License :: OSI Approved :: MIT License
Classifier: Operating System :: OS Independent
Requires-Python: >=3.11
License-File: LICENSE
Provides-Extra: doc
Requires-Dist: sphinx >=7.2.0 ; extra == 'doc'
Requires-Dist: sphinx-rtd-theme >=1.3.0 ; extra == 'doc'
Provides-Extra: test
Requires-Dist: pytest >=7.2.0 ; extra == 'test'
